Metadata-Version: 2.4
Name: djangorestframework-dataclasses
Version: 1.4.0
Summary: A dataclasses serializer for Django REST Framework
Author-email: Oxan van Leeuwen <oxan@oxanvanleeuwen.nl>
License: Copyright (c) 2019-2021, Oxan van Leeuwen
Project-URL: Repository, https://github.com/oxan/djangorestframework-dataclasses
Project-URL: Documentation, https://github.com/oxan/djangorestframework-dataclasses/blob/master/README.rst
Project-URL: Changelog, https://github.com/oxan/djangorestframework-dataclasses/blob/master/CHANGELOG.rst
Project-URL: Sponsor, https://github.com/sponsors/oxan
Classifier: Development Status :: 5 - Production/Stable
Classifier: Environment :: Web Environment
Classifier: Framework :: Django
Classifier: Intended Audience :: Developers
Classifier: License :: OSI Approved :: BSD License
Classifier: Operating System :: OS Independent
Classifier: Programming Language :: Python
Classifier: Topic :: Internet :: WWW/HTTP
Classifier: Topic :: Software Development :: Libraries :: Application Frameworks
Classifier: Topic :: Software Development :: Libraries :: Python Modules
Classifier: Typing :: Typed
Requires-Python: >=3.7
License-File: LICENSE
Requires-Dist: django>=2.0
Requires-Dist: djangorestframework>=3.9
Requires-Dist: typing_extensions>=3.7.4; python_version < "3.8"
Provides-Extra: dev
Requires-Dist: django-stubs; extra == "dev"
Requires-Dist: djangorestframework-stubs; extra == "dev"
Requires-Dist: mypy~=1.15.0; extra == "dev"
Provides-Extra: test
Requires-Dist: coverage[toml]; extra == "test"
Requires-Dist: tox; extra == "test"
Dynamic: license-file
